{
    // 地区建设页面切换地区
    // 单击更换按钮 -> 选择地区（通过锚点指定） -> 单击确认按钮 -> 确认进入地区（通过锚点指定）
    "GoToValleyIV": {
        "doc": "前往四号谷地地区建设界面",
        "recognition": "And",
        "all_of": [
            "InRegionalDevelopment"
        ],
        "next": [
            "InValleyIVRegionalDevelopment",
            "RegionalDevelopmentChangeToValleyIV"
        ]
    },
    "GoToWuling": {
        "doc": "前往武陵地区建设界面",
        "recognition": "And",
        "all_of": [
            "InRegionalDevelopment"
        ],
        "next": [
            "InWulingRegionalDevelopment",
            "RegionalDevelopmentChangeToWuling"
        ]
    },
    "RegionalDevelopmentChangeToValleyIV": {
        "doc": "更改至四号谷地",
        "anchor": {
            "RegionalDevelopmentSelectRegion": "RegionalDevelopmentSelectValleyIV",
            "RegionalDevelopmentInDestinationRegion": "InValleyIVRegionalDevelopment"
        },
        "next": [
            "RegionalDevelopmentEnterChangeRegionMenu"
        ]
    },
    "RegionalDevelopmentChangeToWuling": {
        "doc": "更改至武陵",
        "anchor": {
            "RegionalDevelopmentSelectRegion": "RegionalDevelopmentSelectWuling",
            "RegionalDevelopmentInDestinationRegion": "InWulingRegionalDevelopment"
        },
        "next": [
            "RegionalDevelopmentEnterChangeRegionMenu"
        ]
    },
    "RegionalDevelopmentEnterChangeRegionMenu": {
        "doc": "进入更改地区界面",
        "recognition": "And",
        "all_of": [
            "ChangeRegionButton"
        ],
        "action": "Click",
        "next": [
            "[Anchor]RegionalDevelopmentSelectRegion"
        ]
    },
    "RegionalDevelopmentSelectValleyIV": {
        "doc": "选择四号谷地",
        "recognition": "OCR",
        "order_by": "Expected",
        "roi": [
            429,
            145,
            431,
            165
        ],
        "expected": [
            "四号谷地",
            "四號谷地",
            "Valley IV",
            "Valley",
            "四号谷地",
            "4번 협곡"
        ],
        "action": "Click",
        "next": [
            "RegionalDevelopmentConfirmChangeToRegion"
        ]
    },
    "RegionalDevelopmentSelectWuling": {
        "doc": "选择武陵",
        "recognition": "OCR",
        "order_by": "Expected",
        "roi": [
            429,
            145,
            431,
            165
        ],
        "expected": [
            "武陵",
            "武陵",
            "Wuling",
            "武陵",
            "무릉"
        ],
        "action": "Click",
        "next": [
            "RegionalDevelopmentConfirmChangeToRegion"
        ]
    },
    "RegionalDevelopmentConfirmChangeToRegion": {
        "doc": "确认更改至选定地区",
        "recognition": "And",
        "all_of": [
            "ChangeRegionConfirmButton"
        ],
        "action": "Click",
        "next": [
            "[Anchor]RegionalDevelopmentInDestinationRegion"
        ]
    }
}
