{
    "ValleyIVSwitchToRefugeeCamp": {
        "pre_delay": 0,
        "post_delay": 0,
        "post_wait_freezes": {
            "time": 100,
            "target": [
                811,
                146,
                451,
                542
            ]
        },
        "doc": "OCR 切换至难民暂居处",
        "recognition": {
            "type": "OCR",
            "param": {
                "expected": [
                    "难民暂居处",
                    "難民暫居處",
                    "Refugee Camp",
                    "仮設居住地",
                    "유랑자 임시 거주지"
                ],
                "roi": [
                    146,
                    64,
                    166,
                    34
                ]
            }
        },
        "action": {
            "type": "Click",
            "param": {}
        },
        "next": [
            "ValleyIVVerifyAtRefugeeCamp",
            "ValleyIVSwitchToRefugeeCamp"
        ]
    },
    "ValleyIVVerifyAtRefugeeCamp": {
        "pre_delay": 0,
        "post_delay": 0,
        "post_wait_freezes": {
            "time": 100,
            "target": [
                811,
                146,
                451,
                542
            ]
        },
        "doc": "检测：已切换至难民暂居处",
        "anchor": {
            "SellProductNextOutpost": "ValleyIVSwitchToInfrastructureOutpost"
        },
        "recognition": {
            "type": "ColorMatch",
            "param": {
                "method": 40,
                "roi": [
                    146,
                    64,
                    166,
                    34
                ],
                "lower": [
                    [
                        22,
                        80,
                        180
                    ]
                ],
                "upper": [
                    [
                        36,
                        255,
                        255
                    ]
                ],
                "count": 30
            }
        },
        "next": [
            "SellProductAtSell"
        ]
    },
    "ValleyIVSwitchToInfrastructureOutpost": {
        "pre_delay": 0,
        "post_delay": 0,
        "post_wait_freezes": {
            "time": 100,
            "target": [
                811,
                146,
                451,
                542
            ]
        },
        "doc": "OCR 切换至基建前站",
        "recognition": {
            "type": "OCR",
            "param": {
                "expected": [
                    "基建前站",
                    "Infra-Station",
                    "建設基地",
                    "기초 건설 주둔지"
                ],
                "roi": [
                    447,
                    64,
                    166,
                    34
                ]
            }
        },
        "action": {
            "type": "Click",
            "param": {}
        },
        "next": [
            "ValleyIVVerifyAtInfrastructureOutpost",
            "ValleyIVSwitchToInfrastructureOutpost"
        ]
    },
    "ValleyIVVerifyAtInfrastructureOutpost": {
        "pre_delay": 0,
        "post_delay": 0,
        "post_wait_freezes": {
            "time": 100,
            "target": [
                811,
                146,
                451,
                542
            ]
        },
        "doc": "检测：已切换至基建前站",
        "anchor": {
            "SellProductNextOutpost": "ValleyIVSwitchToReconstructionCommand"
        },
        "recognition": {
            "type": "ColorMatch",
            "param": {
                "method": 40,
                "roi": [
                    447,
                    64,
                    166,
                    34
                ],
                "lower": [
                    [
                        22,
                        80,
                        180
                    ]
                ],
                "upper": [
                    [
                        36,
                        255,
                        255
                    ]
                ],
                "count": 30
            }
        },
        "next": [
            "SellProductAtSell"
        ]
    },
    "ValleyIVSwitchToReconstructionCommand": {
        "pre_delay": 0,
        "post_delay": 0,
        "post_wait_freezes": {
            "time": 100,
            "target": [
                811,
                146,
                451,
                542
            ]
        },
        "doc": "OCR 切换至重建指挥部",
        "recognition": {
            "type": "OCR",
            "param": {
                "expected": [
                    "重建指挥部",
                    "重建指揮部",
                    "Reconstruction HQ",
                    "再建管理本部",
                    "재건 지휘부"
                ],
                "roi": [
                    754,
                    64,
                    166,
                    34
                ]
            }
        },
        "action": {
            "type": "Click",
            "param": {}
        },
        "next": [
            "ValleyIVVerifyAtReconstructionCommand",
            "ValleyIVSwitchToReconstructionCommand"
        ]
    },
    "ValleyIVVerifyAtReconstructionCommand": {
        "pre_delay": 0,
        "post_delay": 0,
        "post_wait_freezes": {
            "time": 100,
            "target": [
                811,
                146,
                451,
                542
            ]
        },
        "doc": "检测：已切换至重建指挥部",
        "anchor": {
            "SellProductNextOutpost": "SellProductRegionEndCheck"
        },
        "recognition": {
            "type": "ColorMatch",
            "param": {
                "method": 40,
                "roi": [
                    754,
                    64,
                    166,
                    34
                ],
                "lower": [
                    [
                        22,
                        80,
                        180
                    ]
                ],
                "upper": [
                    [
                        36,
                        255,
                        255
                    ]
                ],
                "count": 30
            }
        },
        "next": [
            "SellProductAtSell"
        ]
    }
}
